configvars/__init__.py
configvars/apps.py
configvars/management/__init__.py
configvars/management/commands/__init__.py
configvars/management/commands/configvars.py
django_configvars-0.5.post1.dist-info/METADATA
django_configvars-0.5.post1.dist-info/WHEEL
django_configvars-0.5.post1.dist-info/top_level.txt
django_configvars-0.5.post1.dist-info/zip-safe
django_configvars-0.5.post1.dist-info/RECORD
