Metadata-Version: 2.1
Name: django-configvars
Version: 0.5.post1
Summary: Custom settings management for Django
Home-page: https://gitlab.com/marcinjn/django-configvars
Author: Marcin Nowak
Author-email: marcin.j.nowak@gmail.com
Keywords: web python django config settings
Classifier: Development Status :: 4 - Beta
Classifier: Environment :: Web Environment
Classifier: Framework :: Django
Classifier: Framework :: Django :: 3.1
Classifier: Framework :: Django :: 3.2
Classifier: Framework :: Django :: 4.0
Classifier: License :: OSI Approved :: ISC License (ISCL)
Classifier: Operating System :: OS Independent
Classifier: Programming Language :: Python
Classifier: Programming Language :: Python :: 3.9
Classifier: Programming Language :: Python :: 3.10
Classifier: Programming Language :: Python :: 3.11
Classifier: Topic :: Internet :: WWW/HTTP
Classifier: Topic :: Software Development :: Libraries :: Python Modules
Classifier: Intended Audience :: Developers
